mypcremote/__main__.py
mypcremote/commands/__init__.py
mypcremote/commands/beep.py
mypcremote/commands/camera.py
mypcremote/commands/clear.py
mypcremote/commands/hybernate.py
mypcremote/commands/internet.py
mypcremote/commands/kill.py
mypcremote/commands/location.py
mypcremote/commands/lock.py
mypcremote/commands/notify.py
mypcremote/commands/openurl.py
mypcremote/commands/ping.py
mypcremote/commands/reboot.py
mypcremote/commands/screenshot.py
mypcremote/commands/shutdown.py
mypcremote/commands/sleep.py
mypcremote/commands/speak.py
mypcremote/commands/status.py
mypcremote/commands/terminal.py
mypcremote/commands/terminate.py
mypcremote/commands/upload.py
mypcremote/commands/voicecall.py
mypcremote/commands/volume.py
mypcremote-0.6.1.dist-info/LICENSE
mypcremote-0.6.1.dist-info/METADATA
mypcremote-0.6.1.dist-info/WHEEL
mypcremote-0.6.1.dist-info/entry_points.txt
mypcremote-0.6.1.dist-info/top_level.txt
mypcremote-0.6.1.dist-info/RECORD
