Metadata-Version: 2.1
Name: mypcremote
Version: 0.6.1
Summary: A good package to let your computer remote controlled using Discord
Author-email: Zain Ul Abidin <zain26134@gmail.com>
License: MIT License
Project-URL: Homepage, https://github.com/Zedstron/My-PC-Remote
Project-URL: Issues, https://github.com/Zedstron/My-PC-Remote/issues
Keywords: discord,remote,remote-pc,pccontrol,pc-remote,screen-sharing,remote-access,remote-control,pc-management,pc-administration,computer-access,computer-control
Classifier: Programming Language :: Python :: 3
Classifier: License :: OSI Approved :: MIT License
Classifier: Operating System :: Microsoft :: Windows
Requires-Python: >=3.6
License-File: LICENSE
Requires-Dist: python-dotenv
Requires-Dist: tabulate
Requires-Dist: psutil
Requires-Dist: pycaw
Requires-Dist: win10toast
Requires-Dist: speedtest-cli
Requires-Dist: opencv-python
Requires-Dist: discord ==2.3.2
Requires-Dist: pystray ==0.19.5
Requires-Dist: serial ==0.0.97
Requires-Dist: pynmea2 ==1.19.0
Requires-Dist: pyautogui ==0.9.54
Requires-Dist: pyaudio ==0.2.14
Requires-Dist: sounddevice ==0.4.6
